LICENSE.txt
setup.cfg
setup.py
auroraplus/__init__.py
auroraplus.egg-info/PKG-INFO
auroraplus.egg-info/SOURCES.txt
auroraplus.egg-info/dependency_links.txt
auroraplus.egg-info/requires.txt
auroraplus.egg-info/top_level.txt