Metadata-Version: 2.1
Name: auroraplus
Version: 1.5.0
Summary: Python library to access the Aurora+ API: https://api.auroraenergy.com.au/api
Home-page: https://github.com/leighcurran/AuroraPlus
Author: Leigh Curran
Author-email: AuroraPlusPy@outlook.com
License: MIT
Keywords: Aurora+,AuroraPlus,Aurora,Tasmania,API
Platform: UNKNOWN
Classifier: Development Status :: 3 - Alpha
Classifier: Intended Audience :: Developers
Classifier: Topic :: Software Development :: Build Tools
Classifier: License :: OSI Approved :: MIT License
Classifier: Programming Language :: Python :: 3.5
Classifier: Programming Language :: Python :: 3.6
Classifier: Programming Language :: Python :: 3.7
Classifier: Programming Language :: Python :: 3.8
Classifier: Programming Language :: Python :: 3.9
License-File: LICENSE.txt
